{
  "id": "blank_space",
  "type": "SharedSlice",
  "name": "BlankSpace",
  "description": "BlankSpace",
  "variations": [
    {
      "id": "default",
      "name": "Default",
      "docURL": "...",
      "version": "initial",
      "description": "Default",
      "imageUrl": "",
      "primary": {},
      "items": {}
    },
    {
      "id": "small",
      "name": "Small",
      "docURL": "...",
      "version": "initial",
      "description": "Default",
      "imageUrl": "",
      "primary": {},
      "items": {}
    },
    {
      "id": "large",
      "name": "Large",
      "docURL": "...",
      "version": "initial",
      "description": "Default",
      "imageUrl": "",
      "primary": {},
      "items": {}
    }
  ]
}
